<collision>
    <statics count="18">
        <sbc bone="0" type="2" offset="0.0 0.2032851 0.0" size="0.4997799 0.5430305 0.4997799" rotation="0.0 0.0 0.0 1.0"/> <!--Pelvis-->
        <sbc bone="1" type="0" offset="0.0 0.0 0.0" size="0.4555653 0.4555653 0.4555653" rotation="0.0 0.0 0.0 1.0"/> <!--Spine-->
        <sbc bone="1" type="2" offset="0.0 1.0585903 0.0" size="0.4431759 0.7438986 0.4431759" rotation="0.0 0.0 0.0 1.0"/> <!--Spine-->
        
        <sbc bone="2" type="0" offset="0.0 0.0 0.0" size="0.2810833 0.2810833 0.2810833" rotation="0.0 0.0 0.0 1.0"/> <!--L_ArmUp-->
        <sbc bone="2" type="2" offset="0.9468854 0.0094605 0.0" size="0.2134865 0.7240548 0.2134865" rotation="0.0 0.0 -0.7071068 0.7071068"/> <!--L_ArmUp-->
        <sbc bone="3" type="2" offset="0.7813284 -0.0063068 0.0" size="0.1716325 0.6416317 0.1716325" rotation="0.0 0.0 -0.7071068 0.7071068"/> <!--L_Arm-->
        <sbc bone="4" type="2" offset="0.449531 -0.022442 0.0" size="0.1883442 0.2499638 0.1883442" rotation="0.0 0.0 -0.7071068 0.7071068"/> <!--L_Hand-->
        
        <sbc bone="5" type="0" offset="0.0 0.0 0.0" size="0.2810833 0.2810833 0.2810833" rotation="0.0 0.0 0.0 1.0"/> <!--R_ArmUp-->
        <sbc bone="5" type="2" offset="-0.9468854 0.0094605 0.0" size="0.2134865 0.7240548 0.2134865" rotation="0.0 0.0 -0.7071068 0.7071068"/> <!--R_ArmUp-->
        <sbc bone="6" type="2" offset="-0.7813284 -0.0063068 0.0" size="0.1716325 0.6416317 0.1716325" rotation="0.0 0.0 -0.7071068 0.7071068"/> <!--R_Arm-->
        <sbc bone="7" type="2" offset="-0.449531 -0.022442 0.0" size="0.1883442 0.2499638 0.1883442" rotation="0.0 0.0 -0.7071068 0.7071068"/> <!--R_Hand-->
        
        <sbc bone="8" type="2" offset="0.0 0.8242754 0.0" size="0.4047965 0.6468719 0.4047965" rotation="0.0 0.0 0.0 1.0"/> <!--Head-->
        
        <sbc bone="9" type="2" offset="-0.0546079 -1.0751629 0.2195561" size="0.294642 0.9099299 0.2946421" rotation="-0.0933774 0.0136315 -0.0154045 0.9954183"/> <!--L_LegUp-->
        <sbc bone="10" type="2" offset="-0.0448 -1.1707268 -0.1137374" size="0.199819 1.052222 0.1998191" rotation="0.0442461 0.0013864 -0.031 0.9985297"/> <!--L_Leg-->
        <sbc bone="11" type="1" offset="-0.0425769 -0.2667229 0.4880199" size="0.2048242 0.1539151 0.6464608" rotation="0.0017447 -0.0595041 0.0292564 0.9977977"/> <!--L_Foot-->
        
        <sbc bone="12" type="2" offset="0.0546079 -1.0751629 0.2195561" size="0.294642 0.9099299 0.2946421" rotation="-0.0933774 0.0136315 0.0154045 0.9954183"/> <!--R_LegUp-->
        <sbc bone="13" type="2" offset="0.0448 -1.1707268 -0.1137374" size="0.199819 1.052222 0.1998191" rotation="0.0442461 0.0013864 0.031 0.9985297"/> <!--R_Leg-->
        <sbc bone="14" type="1" offset="0.0425769 -0.2667229 0.4880199" size="0.2048242 0.1539151 0.6464608" rotation="0.0017447 0.0595041 -0.0292564 0.9977977"/> <!--R_Foot-->
    </statics>
    <!--<chains count="1">
        <chain count="1" bone="-1">
            <part bone="-1" type="0" size="0.0 0.0 0.0" offset="0.0 0.0 0.0" rotation="0.0 0.0 0.0 1.0"
                mass="1.0" restutition="1.0" friction="1.0" damping="1.0 1.0"
                lowAngLim="0.0 0.0 0.0" uppAngLim="0.0 0.0 0.0" angStiff="0.0 0.0 0.0"
                lowLinLim="0.0 0.0 0.0" uppLinLim="0.0 0.0 0.0" linStiff="0.0 0.0 0.0"
            />
        </chain>
    </chains>-->
</collision>